README.md
setup.cfg
setup.py
ecs_deployer/__init__.py
ecs_deployer.egg-info/PKG-INFO
ecs_deployer.egg-info/SOURCES.txt
ecs_deployer.egg-info/dependency_links.txt
ecs_deployer.egg-info/requires.txt
ecs_deployer.egg-info/top_level.txt
ecs_deployer/bin/ecs-deployer.py