Metadata-Version: 1.2
Name: ecs-deployer
Version: 0.1.6
Summary: Simple Python ECS deployment script.
Home-page: https://github.com/AndySun25/ecs-deployer
Author: Andy Sun
Author-email: andy_sun_sha@hotmail.com
License: MIT
Platform: UNKNOWN
Requires-Python: >3.5
